{
    "Silence Found:": "2024-09-04 15:15:23",
    "ASROutput:  Yeah, it's David.": "2024-09-04 15:15:18",
    "LLMOutput: yes": "2024-09-04 15:15:18",
    "TTS Plays: isp2_yes.wav": "2024-09-04 15:15:18",
    "TTSOutputfe207a31-1089-4e6e-b35c-70064d7bfdf4.wav": "2024-09-04 15:15:18",
    "Detected Voice:": "2024-09-04 15:15:22",
    "ASROutput:  No.": "2024-09-04 15:15:23",
    "LLMOutput: no": "2024-09-04 15:15:23",
    "TTS Plays: isp3_no.wav": "2024-09-04 15:15:22",
    "TTSOutputc6785cd9-b886-47b6-b60b-22e753a213b6.wav": "2024-09-04 15:15:22",
    "Detected interruption": "2024-09-04 15:15:23",
    "TTS Plays: isp5_yes.wav": "2024-09-04 15:15:23",
    "TTSOutput9326490d-d434-4723-939b-afb4ccc45d35.wav": "2024-09-04 15:15:23",
    "Hangup": "2024-09-04 15:15:28"
}